setup.cfg
setup.py
SajadFAS/__init__.py
SajadFAS.egg-info/PKG-INFO
SajadFAS.egg-info/SOURCES.txt
SajadFAS.egg-info/dependency_links.txt
SajadFAS.egg-info/top_level.txt