Metadata-Version: 2.4
Name: SajadFAS
Version: 1.1
Summary: Lib Sajad SxTeam
Author: sajad
Classifier: Programming Language :: Python :: 3
Dynamic: author
Dynamic: classifier
Dynamic: summary
